{
	"data":[
    {"position": 1, "name": "A B Traders", "weight": 1.0079, "symbol": "A G Nagar", "grade":"Mumbai", "contactNo":9876543210, "age":22, "consignorName":"ACK Traders", "consigneeName":"SDE Traders", "cash":1000, "cheque":5000, "chequeNumber":"AB120D1" },
    {"position": 2, "name": "A C Traders", "weight": 4.0026, "symbol": "A G Nagar", "grade":"Bangalore", "contactNo":8876543210, "age":23, "consignorName":"CCK Traders", "consigneeName":"TDE Traders", "cash":1000, "cheque":5000, "chequeNumber":"AB120D2"},
    {"position": 3, "name": "A D Traders", "weight": 6.941, "symbol": "A G Nagar", "grade":"Calicut", "contactNo":7876543210, "age":24, "consignorName":"DCK Traders", "consigneeName":"UDE Traders", "cash":1000, "cheque":5000, "chequeNumber":"AB120D3"},
    {"position": 4, "name": "A E Traders", "weight": 9.0122, "symbol": "A G Nagar", "grade":"Delhi", "contactNo":6876543210, "age":25, "consignorName":"ECK Traders", "consigneeName":"VDE Traders", "cash":1000, "cheque":5000, "chequeNumber":"AB120D4"},
    {"position": 5, "name": "A B Traders", "weight": 10.811, "symbol": "A G Nagar", "grade":"Erode", "contactNo":9876543210, "age":22, "consignorName":"ACK Traders", "consigneeName":"SDE Traders", "cash":1000, "cheque":5000, "chequeNumber":"AB120D5"},
    {"position": 6, "name": "A C Traders", "weight": 12.0107, "symbol": "A G Nagar", "grade":"Mumbai", "contactNo":8876543210, "age":23, "consignorName":"CCK Traders", "consigneeName":"TDE Traders", "cash":1000, "cheque":5000, "chequeNumber":"AB120D6"},
    {"position": 7, "name": "A D Traders", "weight": 14.0067, "symbol": "A G Nagar", "grade":"Bangalore", "contactNo":7876543210, "age":24, "consignorName":"DCK Traders", "consigneeName":"UDE Traders", "cash":1000, "cheque":5000, "chequeNumber":"AB120D7"},
    {"position": 8, "name": "A E Traders", "weight": 15.9994, "symbol": "A G Nagar", "grade":"Calicut", "contactNo":6876543210, "age":25, "consignorName":"ECK Traders", "consigneeName":"VDE Traders", "cash":1000, "cheque":5000, "chequeNumber":"AB120D8"},
    {"position": 9, "name": "A B Traders", "weight": 18.9984, "symbol": "A G Nagar", "grade":"Delhi", "contactNo":9876543210, "age":22, "consignorName":"ACK Traders", "consigneeName":"SDE Traders", "cash":1000, "cheque":5000, "chequeNumber":"AB120D9"},
    {"position": 10, "name": "A C Traders", "weight": 20.1797, "symbol": "A G Nagar", "grade":"Erode", "contactNo":8876543210, "age":23, "consignorName":"CCK Traders", "consigneeName":"TDE Traders", "cash":1000, "cheque":5000, "chequeNumber":"AB120E1"},
    {"position": 9, "name": "A D Traders", "weight": 1.0079, "symbol": "A G Nagar", "grade":"Mumbai", "contactNo":9876543210, "age":22, "consignorName":"ACK Traders", "consigneeName":"SDE Traders", "cash":1000, "cheque":5000, "chequeNumber":"AB120E2"},
    {"position": 8, "name": "A E Traders", "weight": 4.0026, "symbol": "A G Nagar", "grade":"Bangalore", "contactNo":8876543210, "age":23, "consignorName":"CCK Traders", "consigneeName":"TDE Traders", "cash":1000, "cheque":5000, "chequeNumber":"AB120E3"},
    {"position": 7, "name": "A B Traders", "weight": 6.941, "symbol": "A G Nagar", "grade":"Calicut", "contactNo":7876543210, "age":24, "consignorName":"DCK Traders", "consigneeName":"UDE Traders", "cash":1000, "cheque":5000, "chequeNumber":"AB120E4"},
    {"position": 14, "name": "A C Traders", "weight": 9.0122, "symbol": "A G Nagar", "grade":"Delhi", "contactNo":6876543210, "age":25, "consignorName":"ECK Traders", "consigneeName":"VDE Traders", "cash":1000, "cheque":5000, "chequeNumber":"AB120E5"},
    {"position": 15, "name": "A D Traders", "weight": 10.811, "symbol": "A G Nagar", "grade":"Erode", "contactNo":9876543210, "age":22, "consignorName":"ACK Traders", "consigneeName":"SDE Traders", "cash":1000, "cheque":5000, "chequeNumber":"AB120E6"},
    {"position": 16, "name": "A E Traders", "weight": 12.0107, "symbol": "A G Nagar", "grade":"Mumbai", "contactNo":8876543210, "age":23, "consignorName":"CCK Traders", "consigneeName":"TDE Traders", "cash":1000, "cheque":5000, "chequeNumber":"AB120E7"},
    {"position": 17, "name": "A B Traders", "weight": 14.0067, "symbol": "A G Nagar", "grade":"Bangalore", "contactNo":7876543210, "age":24, "consignorName":"DCK Traders", "consigneeName":"UDE Traders", "cash":1000, "cheque":5000, "chequeNumber":"AB120E8"},
    {"position": 18, "name": "A C Traders", "weight": 15.9994, "symbol": "A G Nagar", "grade":"Calicut", "contactNo":6876543210, "age":25, "consignorName":"ECK Traders", "consigneeName":"VDE Traders", "cash":1000, "cheque":5000, "chequeNumber":"AB120E9"},
    {"position": 19, "name": "A D Traders", "weight": 18.9984, "symbol": "A G Nagar", "grade":"Delhi", "contactNo":9876543210, "age":22, "consignorName":"ACK Traders", "consigneeName":"SDE Traders", "cash":1000, "cheque":5000, "chequeNumber":"AB120F1"},
    {"position": 20, "name": "A E Traders", "weight": 20.1797, "symbol": "A G Nagar", "grade":"Erode", "contactNo":8876543210, "age":23, "consignorName":"CCK Traders", "consigneeName":"TDE Traders", "cash":1000, "cheque":5000, "chequeNumber":"AB120F2"}, {"position": 1, "name": "A B Traders", "weight": 1.0079, "symbol": "A G Nagar", "grade":"Mumbai", "contactNo":9876543210, "age":22, "consignorName":"ACK Traders", "consigneeName":"SDE Traders", "cash":1000, "cheque":5000, "chequeNumber":"AB120D1" },
    {"position": 19, "name": "A C Traders", "weight": 4.0026, "symbol": "A G Nagar", "grade":"Bangalore", "contactNo":8876543210, "age":23, "consignorName":"CCK Traders", "consigneeName":"TDE Traders", "cash":1000, "cheque":5000, "chequeNumber":"AB120D2"},
    {"position": 3, "name": "A D Traders", "weight": 6.941, "symbol": "A G Nagar", "grade":"Calicut", "contactNo":7876543210, "age":24, "consignorName":"DCK Traders", "consigneeName":"UDE Traders", "cash":1000, "cheque":5000, "chequeNumber":"AB120D3"},
    {"position": 4, "name": "A E Traders", "weight": 9.0122, "symbol": "A G Nagar", "grade":"Delhi", "contactNo":6876543210, "age":25, "consignorName":"ECK Traders", "consigneeName":"VDE Traders", "cash":1000, "cheque":5000, "chequeNumber":"AB120D4"},
    {"position": 5, "name": "A B Traders", "weight": 10.811, "symbol": "A G Nagar", "grade":"Erode", "contactNo":9876543210, "age":22, "consignorName":"ACK Traders", "consigneeName":"SDE Traders", "cash":1000, "cheque":5000, "chequeNumber":"AB120D5"},
    {"position": 6, "name": "A C Traders", "weight": 12.0107, "symbol": "A G Nagar", "grade":"Mumbai", "contactNo":8876543210, "age":23, "consignorName":"CCK Traders", "consigneeName":"TDE Traders", "cash":1000, "cheque":5000, "chequeNumber":"AB120D6"},
    {"position": 7, "name": "A D Traders", "weight": 14.0067, "symbol": "A G Nagar", "grade":"Bangalore", "contactNo":7876543210, "age":24, "consignorName":"DCK Traders", "consigneeName":"UDE Traders", "cash":1000, "cheque":5000, "chequeNumber":"AB120D7"},
    {"position": 8, "name": "A E Traders", "weight": 15.9994, "symbol": "A G Nagar", "grade":"Calicut", "contactNo":6876543210, "age":25, "consignorName":"ECK Traders", "consigneeName":"VDE Traders", "cash":1000, "cheque":5000, "chequeNumber":"AB120D8"},
    {"position": 9, "name": "A B Traders", "weight": 18.9984, "symbol": "A G Nagar", "grade":"Delhi", "contactNo":9876543210, "age":22, "consignorName":"ACK Traders", "consigneeName":"SDE Traders", "cash":1000, "cheque":5000, "chequeNumber":"AB120D9"},
    {"position": 10, "name": "A C Traders", "weight": 20.1797, "symbol": "A G Nagar", "grade":"Erode", "contactNo":8876543210, "age":23, "consignorName":"CCK Traders", "consigneeName":"TDE Traders", "cash":1000, "cheque":5000, "chequeNumber":"AB120E1"},
    {"position": 11, "name": "A D Traders", "weight": 1.0079, "symbol": "A G Nagar", "grade":"Mumbai", "contactNo":9876543210, "age":22, "consignorName":"ACK Traders", "consigneeName":"SDE Traders", "cash":1000, "cheque":5000, "chequeNumber":"AB120E2"},
    {"position": 12, "name": "A E Traders", "weight": 4.0026, "symbol": "A G Nagar", "grade":"Bangalore", "contactNo":8876543210, "age":23, "consignorName":"CCK Traders", "consigneeName":"TDE Traders", "cash":1000, "cheque":5000, "chequeNumber":"AB120E3"},
    {"position": 13, "name": "A B Traders", "weight": 6.941, "symbol": "A G Nagar", "grade":"Calicut", "contactNo":7876543210, "age":24, "consignorName":"DCK Traders", "consigneeName":"UDE Traders", "cash":1000, "cheque":5000, "chequeNumber":"AB120E4"},
    {"position": 14, "name": "A C Traders", "weight": 9.0122, "symbol": "A G Nagar", "grade":"Delhi", "contactNo":6876543210, "age":25, "consignorName":"ECK Traders", "consigneeName":"VDE Traders", "cash":1000, "cheque":5000, "chequeNumber":"AB120E5"},
    {"position": 15, "name": "A D Traders", "weight": 10.811, "symbol": "A G Nagar", "grade":"Erode", "contactNo":9876543210, "age":22, "consignorName":"ACK Traders", "consigneeName":"SDE Traders", "cash":1000, "cheque":5000, "chequeNumber":"AB120E6"},
    {"position": 16, "name": "A E Traders", "weight": 12.0107, "symbol": "A G Nagar", "grade":"Mumbai", "contactNo":8876543210, "age":23, "consignorName":"CCK Traders", "consigneeName":"TDE Traders", "cash":1000, "cheque":5000, "chequeNumber":"AB120E7"},
    {"position": 17, "name": "A B Traders", "weight": 14.0067, "symbol": "A G Nagar", "grade":"Bangalore", "contactNo":7876543210, "age":24, "consignorName":"DCK Traders", "consigneeName":"UDE Traders", "cash":1000, "cheque":5000, "chequeNumber":"AB120E8"},
    {"position": 18, "name": "A C Traders", "weight": 15.9994, "symbol": "A G Nagar", "grade":"Calicut", "contactNo":6876543210, "age":25, "consignorName":"ECK Traders", "consigneeName":"VDE Traders", "cash":1000, "cheque":5000, "chequeNumber":"AB120E9"},
    {"position": 19, "name": "A D Traders", "weight": 18.9984, "symbol": "A G Nagar", "grade":"Delhi", "contactNo":9876543210, "age":22, "consignorName":"ACK Traders", "consigneeName":"SDE Traders", "cash":1000, "cheque":5000, "chequeNumber":"AB120F1"},
    {"position": 20, "name": "A E Traders", "weight": 20.1797, "symbol": "A G Nagar", "grade":"Erode", "contactNo":8876543210, "age":23, "consignorName":"CCK Traders", "consigneeName":"TDE Traders", "cash":1000, "cheque":5000, "chequeNumber":"AB120F2"}
    ]
}